widgyts/__init__.py
widgyts/_version.py
widgyts/image_canvas.py
widgyts/colormaps/__init__.py
widgyts/colormaps/colormaps.py
widgyts/static/0.index.js
widgyts/static/0.index.js.map
widgyts/static/bbdba2be3ee75f23889f.module.wasm
widgyts/static/extension.js
widgyts/static/index.js
widgyts/static/index.js.map
widgyts-0.3.1.data/data/etc/jupyter/jupyter_notebook_config.d/widgyts.json
widgyts-0.3.1.data/data/etc/jupyter/nbconfig/notebook.d/widgyts.json
widgyts-0.3.1.data/data/share/jupyter/nbextensions/yt-widgets/0.index.js
widgyts-0.3.1.data/data/share/jupyter/nbextensions/yt-widgets/0.index.js.map
widgyts-0.3.1.data/data/share/jupyter/nbextensions/yt-widgets/bbdba2be3ee75f23889f.module.wasm
widgyts-0.3.1.data/data/share/jupyter/nbextensions/yt-widgets/extension.js
widgyts-0.3.1.data/data/share/jupyter/nbextensions/yt-widgets/index.js
widgyts-0.3.1.data/data/share/jupyter/nbextensions/yt-widgets/index.js.map
widgyts-0.3.1.dist-info/METADATA
widgyts-0.3.1.dist-info/RECORD
widgyts-0.3.1.dist-info/WHEEL
widgyts-0.3.1.dist-info/top_level.txt
